_pyejdb
pyejdb
