Metadata-Version: 1.1
Name: pyejdb
Version: 1.0.16
Summary: Python 2.7/3.x binding for EJDB database engine.
Home-page: http://ejdb.org
Author: Adamansky Anton
Author-email: adamansky@gmail.com
License: GNU Lesser General Public License (LGPL)
Keywords: ejdb,tokyocabinet,nosql,database,storage,embedded,mongodb,json
Platform: UNKNOWN
Classifier: Development Status :: 4 - Beta
Classifier: Intended Audience :: Developers
Classifier: License :: OSI Approved :: GNU Lesser General Public License v2 (LGPLv2)
Classifier: Operating System :: POSIX
Classifier: Operating System :: MacOS :: MacOS X
Classifier: Operating System :: Microsoft :: Windows
Classifier: Programming Language :: Python :: 2.7
Classifier: Programming Language :: Python :: 2
Classifier: Programming Language :: Python :: 3.2
Classifier: Programming Language :: Python :: 3.3
Classifier: Programming Language :: Python :: 3.4
Classifier: Programming Language :: Python :: 3
Classifier: Topic :: Software Development :: Libraries
